MANIFEST.in
README.md
setup.py
soocii_pubsub_lib/__init__.py
soocii_pubsub_lib/pubsub_client.py
soocii_pubsub_lib/sub_service.py
soocii_pubsub_lib.egg-info/PKG-INFO
soocii_pubsub_lib.egg-info/SOURCES.txt
soocii_pubsub_lib.egg-info/dependency_links.txt
soocii_pubsub_lib.egg-info/not-zip-safe
soocii_pubsub_lib.egg-info/requires.txt
soocii_pubsub_lib.egg-info/top_level.txt