Metadata-Version: 2.1
Name: soocii-pubsub-lib
Version: 1.2
Summary: Library for Soocii back-end services to integrate with Google Cloud Pub/Sub service.
Home-page: https://github.com/drmobile/pubsub-broker
Author: Soocii
Author-email: service@soocii.me
License: Apache Software License
Platform: UNKNOWN
Classifier: Development Status :: 4 - Beta
Classifier: Intended Audience :: Developers
Classifier: Topic :: Software Development :: Libraries :: Python Modules
Classifier: License :: OSI Approved :: Apache Software License
Classifier: Programming Language :: Python :: 2.7
Classifier: Programming Language :: Python :: 3.5
Provides-Extra: dev
